{
  "parent": "jolcraft:story/trade_brewmaster",
  "criteria": {
    "endorse_brewmaster": {
      "conditions": {
        "profession": "jolcraft:dwarf_brewmaster"
      },
      "trigger": "jolcraft:endorsement_gain"
    }
  },
  "display": {
    "description": {
      "translate": "advancement.jolcraft.brewmaster.endorse.description"
    },
    "frame": "goal",
    "icon": {
      "count": 1,
      "id": "jolcraft:reputation_tablet_1"
    },
    "title": {
      "translate": "advancement.jolcraft.brewmaster.endorse.title"
    }
  },
  "requirements": [
    [
      "endorse_brewmaster"
    ]
  ],
  "sends_telemetry_event": true
}